arcadeutils/README.md
arcadeutils/__init__.py
arcadeutils/binary.py
arcadeutils/filebytes.py
arcadeutils/py.typed
arcadeutils-0.1.11.dist-info/LICENSE
arcadeutils-0.1.11.dist-info/METADATA
arcadeutils-0.1.11.dist-info/WHEEL
arcadeutils-0.1.11.dist-info/top_level.txt
arcadeutils-0.1.11.dist-info/RECORD
