Metadata-Version: 2.1
Name: arcadeutils
Version: 0.1.11
Summary: Collection of utilities written in Python for working with various arcade binaries.
Home-page: https://github.com/DragonMinded/arcadeutils
Author: DragonMinded
Author-email: dragonminded@dragonminded.com
License: Public Domain
Platform: UNKNOWN
Requires-Python: >=3.6
License-File: LICENSE
Requires-Dist: typing-extensions
